serdesripy-0.1.2.dist-info/METADATA
serdesripy-0.1.2.dist-info/WHEEL
serdesripy/__init__.py
serdesripy/serdesripy.cpython-38-x86_64-linux-gnu.so
serdesripy-0.1.2.dist-info/RECORD
