Metadata-Version: 2.1
Name: serdesripy
Version: 0.1.2
Classifier: Programming Language :: Rust
Classifier: Programming Language :: Python :: Implementation :: CPython
Classifier: Programming Language :: Python :: Implementation :: PyPy
Requires-Dist: pyarrow ~=11.0.0
Requires-Python: >=3.8
